litepolis_database_example/Actor.py
litepolis_database_example/Comments.py
litepolis_database_example/Conversations.py
litepolis_database_example/Users.py
litepolis_database_example/__init__.py
litepolis_database_example/utils.py
litepolis_database_example-0.0.2.dist-info/licenses/LICENSE
litepolis_database_example-0.0.2.dist-info/METADATA
litepolis_database_example-0.0.2.dist-info/WHEEL
litepolis_database_example-0.0.2.dist-info/top_level.txt
litepolis_database_example-0.0.2.dist-info/RECORD
